{
  "results": [
    {
      "topic": "Photoshop 2020",
      "name": "ফটোশপ সফটওয়্যার ২০২০",
      "image": "https://faridrony55.github.io/support_data/photoshop.png",
      "details": "ডাউনলোড করে নিন ফটোশপ ভার্সন ২০২০।  সফটওয়ারটি ডাউনলোড করতে নিচের লিংক এ  ক্লিক করুন।<br> <a target='blank' href='https://drive.google.com/file/d/1r2hBk9H-3H34lv0Uxmf102RdJt7SG6KE/view?usp=sharing'>ডাউনলোডের জন্য ক্লিক করুন </a> <br>  এটি কিন্তু  ক্র্যাক ভার্সন।  সুতরাং ইনস্টল করতে অবশ্যই আপনার কম্পিউটারের ইন্টারনেট কানেকশন বন্ধ করে নিন।   <br> প্রয়োজনে ভিডিওটি দেখুন: "
    },
    {
      "topic": "Photoshop 2019",
      "name": "ফটোশপ সফটওয়্যার ২০১৯",
      "image": "https://faridrony55.github.io/support_data/photoshop.png",
      "details": "ডাউনলোড করে নিন ফটোশপ ভার্সন ২০১৯  সফটওয়ারটি ডাউনলোড করতে নিচের লিংক এ  ক্লিক করুন।<br> <a target='blank' href='https://drive.google.com/file/d/11cc8JRm3vrm5Co_uu-QStFCyxvx4hFpL/view?usp=sharing'>ডাউনলোডের জন্য ক্লিক করুন </a> <br>  এটি কিন্তু  ক্র্যাক ভার্সন।  সুতরাং ইনস্টল করতে অবশ্যই আপনার কম্পিউটারের ইন্টারনেট কানেকশন বন্ধ করে নিন।   <br> প্রয়োজনে ভিডিওটি দেখুন: "
    },
    {
      "topic": "Photoshop Portable",
      "name": "ফটোশপ সফটওয়্যার পোর্টেবল",
      "image": "https://faridrony55.github.io/support_data/photoshop.png",
      "details": "ডাউনলোড করে নিন ফটোশপ পোর্টেবল ভার্সন । সফটওয়ারটি ডাউনলোড করতে নিচের লিংক এ  ক্লিক করুন।<br> <a target='blank' href='https://drive.google.com/file/d/11cc8JRm3vrm5Co_uu-QStFCyxvx4hFpL/view?usp=sharing'>ডাউনলোডের জন্য ক্লিক করুন </a> <br>  এটি কিন্তু  ক্র্যাক ভার্সন।  সুতরাং ইনস্টল করতে অবশ্যই আপনার কম্পিউটারের ইন্টারনেট কানেকশন বন্ধ করে নিন।   <br> প্রয়োজনে ভিডিওটি দেখুন: "
    },
    {
      "topic": "Illustrator 2020",
      "name": "ইলাস্ট্রেটর সফটওয়্যার ২০২০",
      "image": "https://faridrony55.github.io/support_data/illustrator.png",
      "details": "ডাউনলোড করে নিন ইলাস্ট্রেটর ভার্সন ২০২০।  সফটওয়ারটি ডাউনলোড করতে নিচের লিংক এ  ক্লিক করুন।<br> <a target='blank' href='https://drive.google.com/file/d/18L4f4w2OAtDbfp-Gl0K3yViP81XRUssw/view?usp=sharing'>ডাউনলোডের জন্য ক্লিক করুন </a> <br>  এটি কিন্তু  ক্র্যাক ভার্সন।  সুতরাং ইনস্টল করতে অবশ্যই আপনার কম্পিউটারের ইন্টারনেট কানেকশন বন্ধ করে নিন।   <br> প্রয়োজনে ভিডিওটি দেখুন: "
    },
    {
      "topic": "Illustrator 2019",
      "name": "ইলাস্ট্রেটর সফটওয়্যার ২০১৯",
      "image": "https://faridrony55.github.io/support_data/illustrator.png",
      "details": "ডাউনলোড করে নিন ইলাস্ট্রেটর ভার্সন ২০১৯  সফটওয়ারটি ডাউনলোড করতে নিচের লিংক এ  ক্লিক করুন।<br> <a target='blank' href='https://drive.google.com/file/d/14gJxbYlEXMJJ4jQVoVS-VjZ4Z87ynC6d/view?usp=sharing'>ডাউনলোডের জন্য ক্লিক করুন </a> <br>  এটি কিন্তু  ক্র্যাক ভার্সন।  সুতরাং ইনস্টল করতে অবশ্যই আপনার কম্পিউটারের ইন্টারনেট কানেকশন বন্ধ করে নিন।   <br> প্রয়োজনে ভিডিওটি দেখুন: "
    },
    {
      "topic": "Wordpress theme",
      "name": "ওয়ার্ডপ্রেস থিম",
      "image": "https://faridrony55.github.io/support_data/wordpress.png",
      "details": "খুব শিঘ্রই পাবেন"
    },
    {
      "topic": "Wordpress plugin",
      "name": "ওয়ার্ডপ্রেস প্লাগিন",
      "image": "https://faridrony55.github.io/support_data/wordpress.png",
      "details": "খুব শিঘ্রই পাবেন"
    },
    {
      "topic": "Shopify Theme",
      "name": "শপিফাই থিম",
      "image": "https://faridrony55.github.io/support_data/shopify.png",
      "details": "খুব শিঘ্রই পাবেন"
    } 
     
  ]
}
